{
  "word": "bypass",
  "senses": [
    {
      "headword": "bypass (n.)",
      "text": "also by-pass, 1848, of certain pipes in a gasworks, from by + pass (n.). First used 1922 for \"road for the relief of congestion;\" figurative sense is from 1928. The heart operation was first so called 1957."
    },
    {
      "headword": "bypass (v.)",
      "text": "1823, \"to pass by\" (implied in bypassed), from bypass (n.). From 1928 as \"to go around, avoid;\" figurative use from 1941. Related: Bypassed; bypassing."
    }
  ]
}
