{
  "word": "dose",
  "senses": [
    {
      "headword": "dose (n.)",
      "text": "early 15c., \"the giving of medicine (in a specified amount or at a stated time),\" from Middle French dose (15c.) or directly from Late Latin dosis, from Greek dosis \"a portion prescribed,\" literally \"a giving,\" used by Galen and other Greek physicians to mean an amount of medicine, from stem of didonai \"to give\" (see date (n.1)). Slang meaning \"venereal disease\" is from 1914."
    },
    {
      "headword": "dose (v.)",
      "text": "1650s, from dose (n.). Related: Dosed; dosing."
    }
  ]
}
