{
  "word": "reverence",
  "senses": [
    {
      "headword": "reverence (n.)",
      "text": "late 13c., from Old French reverence \"respect, awe,\" from Latin reverentia \"awe, respect,\" from revereri \"to stand in awe of, respect, honor, fear, be afraid of; revere,\" from re-, intensive prefix (see re-), + vereri \"stand in awe of, fear, respect,\" from PIE *wer-e-, suffixed form of root *wer- (4) \"to be or become aware of, perceive, watch out for\" (see ward (n.))."
    },
    {
      "headword": "reverence (v.)",
      "text": "late 14c., \"treat with respect, honor; venerate, pay pious homage to; esteem, value; bow to (someone); do honor to,\" from reverence (n.). Related: Reverenced; reverencing."
    }
  ]
}
